refcount-1.2.7.dist-info/METADATA
refcount-1.2.7.dist-info/WHEEL
refcount-1.2.7.dist-info/entry_points.txt
refcount-1.2.7.dist-info/licenses/LICENSE
refcount-1.2.7.dist-info/licenses/LICENSE.txt
refcount/.ruff_cache/.gitignore
refcount/.ruff_cache/0.9.1/18301329075957192798
refcount/.ruff_cache/CACHEDIR.TAG
refcount/__init__.py
refcount/base.py
refcount/debug.py
refcount/interop.py
refcount/putils.py
refcount/py.typed
refcount-1.2.7.dist-info/RECORD
