Metadata-Version: 2.1
Name: refcount
Version: 1.2.7
Summary: Python classes for reference counting
Author-Email: J-M <jean-michel.perraud@csiro.au>
License: MIT
Classifier: Development Status :: 5 - Production/Stable
Classifier: Intended Audience :: Developers
Classifier: Programming Language :: Python
Classifier: Programming Language :: Python :: 3
Classifier: Programming Language :: Python :: 3 :: Only
Classifier: Programming Language :: Python :: 3.9
Classifier: Programming Language :: Python :: 3.10
Classifier: Programming Language :: Python :: 3.11
Classifier: Programming Language :: Python :: 3.12
Classifier: Programming Language :: Python :: 3.13
Classifier: Topic :: Documentation
Classifier: Topic :: Software Development
Classifier: Topic :: Utilities
Classifier: Typing :: Typed
Project-URL: Homepage, https://csiro-hydroinformatics.github.io/pyrefcount
Project-URL: Documentation, https://csiro-hydroinformatics.github.io/pyrefcount
Project-URL: Changelog, https://csiro-hydroinformatics.github.io/pyrefcount/changelog
Project-URL: Repository, https://github.com/csiro-hydroinformatics/pyrefcount
Project-URL: Issues, https://github.com/csiro-hydroinformatics/pyrefcount/issues
Requires-Python: >=3.9
Requires-Dist: cffi>=1.17
